llama_index/llms/maritalk/__init__.py
llama_index/llms/maritalk/base.py
llama_index_llms_maritalk-0.5.1.dist-info/METADATA
llama_index_llms_maritalk-0.5.1.dist-info/WHEEL
llama_index_llms_maritalk-0.5.1.dist-info/licenses/LICENSE
llama_index_llms_maritalk-0.5.1.dist-info/RECORD
