Metadata-Version: 2.4
Name: llama-index-llms-maritalk
Version: 0.5.1
Summary: llama-index llms maritalk integration
Author-email: Your Name <you@example.com>
License-Expression: MIT
License-File: LICENSE
Requires-Python: <3.12,>=3.9
Requires-Dist: llama-index-core<0.15,>=0.13.0
